localstack_extension_authress/__init__.py
localstack_extension_authress/extension.py
localstack_extension_authress/server.py
localstack_extension_authress-0.1.24.dist-info/LICENSE
localstack_extension_authress-0.1.24.dist-info/METADATA
localstack_extension_authress-0.1.24.dist-info/WHEEL
localstack_extension_authress-0.1.24.dist-info/entry_points.txt
localstack_extension_authress-0.1.24.dist-info/top_level.txt
localstack_extension_authress-0.1.24.dist-info/RECORD
