Metadata-Version: 2.1
Name: localstack-extension-authress
Version: 0.1.24
Summary: LocalStack Extension: Authress
Home-page: https://github.com/authress/authress-local
Author: Authress
Author-email: developers@authress.io
License: AGPL-3.0
Keywords: Authorization as a service,Security,authorization,authorization as a service,authentication,user authentication,Authress,Authress client,access management,access management as a service,user security,localstack,localstack extensions,verified,verified access,verified permissions,open source policy engine,embedded authorization,batteries included authorization
License-File: LICENSE
Requires-Dist: localstack >=2.2.1.dev20230812232603
Requires-Dist: authress >=3.0.78
